cslavonic/__init__.py
cslavonic/calendar.py
cslavonic/convert.py
cslavonic/cu_codechart.py
cslavonic/cu_normalize.py
cslavonic/cu_reencode.py
cslavonic/normalize.py
cslavonic/numerals.py
cslavonic/test_calendar.py
cslavonic/test_convert.py
cslavonic/test_normalize.py
cslavonic/test_numerals.py
cslavonic/test_tokenize.py
cslavonic/tokenize.py
cslavonic/ucs_codec.py
cslavonic/ucs_decode.py
cslavonic/resources/untitlo.tsv
cslavonic-0.5.2.dist-info/METADATA
cslavonic-0.5.2.dist-info/RECORD
cslavonic-0.5.2.dist-info/WHEEL
cslavonic-0.5.2.dist-info/entry_points.txt
cslavonic-0.5.2.dist-info/top_level.txt
