Metadata-Version: 2.1
Name: cslavonic
Version: 0.5.2
Summary: Utilities for working with Church Slavonic language
Home-page: https://github.com/pgmmpk/cslavonic
Author: Mike Kroutikov
Author-email: pgmmpk@gmail.com
License: MIT
Keywords: church slavonic language
Platform: UNKNOWN
Classifier: Development Status :: 4 - Beta
Classifier: Intended Audience :: Developers
Classifier: Intended Audience :: Education
Classifier: Intended Audience :: Religion
Classifier: Intended Audience :: Science/Research
Classifier: License :: OSI Approved :: MIT License
Classifier: Programming Language :: Python :: 2.7
Classifier: Programming Language :: Python :: 3
Requires-Dist: fonttools
